Psience/__init__.py
Psience/AIMD/Simulator.py
Psience/AIMD/__init__.py
Psience/AnalyticModels/AnalyticJacobianDotCalculator.py
Psience/AnalyticModels/AnalyticModelConstructors.py
Psience/AnalyticModels/Helpers.py
Psience/AnalyticModels/__init__.py
Psience/BasisReps/Bases.py
Psience/BasisReps/ClassicalBases.py
Psience/BasisReps/HarmonicOscillator.py
Psience/BasisReps/Local.py
Psience/BasisReps/Operators.py
Psience/BasisReps/Representations.py
Psience/BasisReps/StateFilters.py
Psience/BasisReps/StateIndexers.py
Psience/BasisReps/StateSpaces.py
Psience/BasisReps/Util.py
Psience/BasisReps/Wavefunctions.py
Psience/BasisReps/__init__.py
Psience/DGB/Coordinates.py
Psience/DGB/DGB.py
Psience/DGB/Evaluators.py
Psience/DGB/Gaussians.py
Psience/DGB/Interpolation.py
Psience/DGB/Runners.py
Psience/DGB/Solvers.py
Psience/DGB/Wavefunctions.py
Psience/DGB/__init__.py
Psience/DVR/BaseDVR.py
Psience/DVR/ColbertMiller.py
Psience/DVR/DVR.py
Psience/DVR/DirectProduct.py
Psience/DVR/Extensions.py
Psience/DVR/FiniteBasisDVR.py
Psience/DVR/Wavefunctions.py
Psience/DVR/__init__.py
Psience/Data/KEData.py
Psience/Data/PotentialRegistry.py
Psience/Data/Surfaces.py
Psience/Data/__init__.py
Psience/Data/PsiDatasets/KEData.py
Psience/Data/PsiDatasets/__init__.py
Psience/Modes/Coordinates.py
Psience/Modes/LocalizedModes.py
Psience/Modes/MixtureModes.py
Psience/Modes/NormalModes.py
Psience/Modes/ObliqueModes.py
Psience/Modes/__init__.py
Psience/Molecools/CoordinateSystems.py
Psience/Molecools/Evaluator.py
Psience/Molecools/Hamiltonian.py
Psience/Molecools/MolecularFunctionExpansion.py
Psience/Molecools/Molecule.py
Psience/Molecools/MoleculeInterface.py
Psience/Molecools/Properties.py
Psience/Molecools/Serializers.py
Psience/Molecools/Transformations.py
Psience/Molecools/Vibrations.py
Psience/Molecools/__init__.py
Psience/Nonlinear/NonlinearResponse.py
Psience/Nonlinear/__init__.py
Psience/Plots/EnergyLevelDiagram.py
Psience/Plots/__init__.py
Psience/Reactions/AtomMapper.py
mccoygroup_psience-1.3.7.dist-info/licenses/LICENSE.txt
mccoygroup_psience-1.3.7.dist-info/METADATA
mccoygroup_psience-1.3.7.dist-info/WHEEL
mccoygroup_psience-1.3.7.dist-info/top_level.txt
mccoygroup_psience-1.3.7.dist-info/RECORD
