Metadata-Version: 2.4
Name: mccoygroup-psience
Version: 1.3.7
Author: Mark Boyer
Author-email: maboyer@tamu.edu
License: MIT
Requires-Python: >=3.9
License-File: LICENSE.txt
Requires-Dist: mccoygroup-mcutils>=1.5.11
Dynamic: author
Dynamic: author-email
Dynamic: description
Dynamic: description-content-type
Dynamic: license
Dynamic: license-file
Dynamic: requires-dist
Dynamic: requires-python
